pararead/__init__.py
pararead/_version.py
pararead/exceptions.py
pararead/processor.py
pararead/utils.py
pararead-0.8.0.dist-info/LICENSE.txt
pararead-0.8.0.dist-info/METADATA
pararead-0.8.0.dist-info/WHEEL
pararead-0.8.0.dist-info/top_level.txt
pararead-0.8.0.dist-info/RECORD
